jinjaql/__init__.py
jinjaql/cache.py
jinjaql/convertors.py
jinjaql/engine.py
jinjaql/factory.py
jinjaql/tests/__init__.py
jinjaql/tests/test_guards.py
jinjaql/tests/test_integration.py
jinjaql/tests/test_integration_engine_cache.py
jinjaql/tests/test_migrations.py
jinjaql/tests/test_schema.py
jinjaql/tests/test_usage.py
jinjaql-0.2.1.dist-info/LICENSE
jinjaql-0.2.1.dist-info/METADATA
jinjaql-0.2.1.dist-info/WHEEL
jinjaql-0.2.1.dist-info/top_level.txt
jinjaql-0.2.1.dist-info/RECORD
