Metadata-Version: 2.1
Name: jinjaql
Version: 0.2.1
Summary: Transparant *QL usage without ORM
Home-page: https://github.com/RichFoley/jinjaql
Author: Richard Foley and David Smit (based on the work of Roman Zaiev)
Author-email: david.d.smit@gmail.com
License: MIT
Platform: UNKNOWN
Classifier: Intended Audience :: Developers
Classifier: License :: OSI Approved :: MIT License
Classifier: Operating System :: OS Independent
Classifier: Programming Language :: Python
Classifier: Programming Language :: Python :: 3.5
Classifier: Programming Language :: Python :: 3.6
Classifier: Programming Language :: Python :: 3.7
Classifier: Topic :: Software Development :: Libraries :: Python Modules
Requires-Dist: Jinja2 (>=2.9.5)
Requires-Dist: schema (>=0.6.5)
